adam_atan2_pytorch/__init__.py
adam_atan2_pytorch/adam_atan2.py
adam_atan2_pytorch/adam_atan2_with_wasserstein_reg.py
adam_atan2_pytorch/adopt.py
adam_atan2_pytorch/adopt_atan2.py
adam_atan2_pytorch/foreach.py
adam_atan2_pytorch/muon_adam_atan2.py
adam_atan2_pytorch-0.2.4.dist-info/METADATA
adam_atan2_pytorch-0.2.4.dist-info/WHEEL
adam_atan2_pytorch-0.2.4.dist-info/licenses/LICENSE
adam_atan2_pytorch-0.2.4.dist-info/RECORD
