Metadata-Version: 2.4
Name: adam-atan2-pytorch
Version: 0.2.4
Summary: Adam-atan2 for Pytorch
Project-URL: Homepage, https://pypi.org/project/adam_atan2_pytorch/
Project-URL: Repository, https://github.com/lucidrains/adam_atan2_pytorch
Author-email: Phil Wang <lucidrains@gmail.com>
License: MIT License
License-File: LICENSE
Keywords: adam,artificial intelligence,deep learning,optimizers
Classifier: Development Status :: 4 - Beta
Classifier: Intended Audience :: Developers
Classifier: License :: OSI Approved :: MIT License
Classifier: Programming Language :: Python :: 3.9
Classifier: Topic :: Scientific/Engineering :: Artificial Intelligence
Requires-Python: >=3.9
Requires-Dist: torch>=2.0
Provides-Extra: examples
Provides-Extra: test
Requires-Dist: pytest; extra == 'test'
